<?xml version="1.0" encoding="utf-8" ?>
<Defs>
	<ThingDef ParentName="ESCP_SprigganThingBase">
		<defName>ESCP_Spriggan_EarthMother</defName>
		<label>spriggan earth mother</label>
		<description>Spriggans are creatures of wood and psychic energy, concentrated into a being that is immensely concerned with the well being of plant life. Often attacking anything threatening or damaging forested areas, as well as hiding or laying in ambush in such areas, spriggans come in all shapes and sizes living in most biomes that have some vegetation.\n\nAlthough a spriggan may only have its wood skin for protection, they are still quite a threat to people if angered. Long sharp claws as well as the ability to call upon animals to protect the forest makes them a great threat to trespassers, or a boon to those willing to risk everything to befriend one of them. Spriggans also have an innate healing ability when close to death.\n\nEarth Mother Spriggans should be feared above all other spriggans, they have no mercy for any creature who would harm the forest and hold all in great contempt. Having seen a great many years and transformed into a earth mother she will be the forests greatest guardian and can be found in any biome with plant life, although she is quite rare.</description>
		<descriptionHyperlinks>
			<ThingDef>ESCP_SprigganTaproot_Mother</ThingDef>
			<ThingDef MayRequire="Ludeon.RimWorld.Ideology">ESCP_SprigganTree_Mother</ThingDef>
		</descriptionHyperlinks>
		<statBases>
			<MoveSpeed>4.4</MoveSpeed>
			<ArmorRating_Blunt>0.12</ArmorRating_Blunt>
			<ArmorRating_Sharp>0.15</ArmorRating_Sharp>
			<MarketValue>650</MarketValue>
		</statBases>
		<tools Inherit="False">
			<!-- hands -->
			<li>
				<label>fist</label>
				<capacities>
					<li>Blunt</li>
				</capacities>
				<power>16</power>
				<cooldownTime>1.5</cooldownTime>
				<linkedBodyPartsGroup>Hands</linkedBodyPartsGroup>
				<surpriseAttack>
					<extraMeleeDamages>
						<li>
							<def>Stun</def>
							<amount>18</amount>
						</li>
					</extraMeleeDamages>
				</surpriseAttack>
			</li>
			<li>
				<label>left claw</label>
				<capacities>
					<li>Scratch</li>
				</capacities>
				<power>18</power>
				<cooldownTime>1.2</cooldownTime>
				<linkedBodyPartsGroup>FrontLeftClaws</linkedBodyPartsGroup>
				<surpriseAttack>
					<extraMeleeDamages>
						<li>
							<def>Stun</def>
							<amount>10</amount>
						</li>
					</extraMeleeDamages>
				</surpriseAttack>
			</li>
			<li>
				<label>right claw</label>
				<capacities>
					<li>Scratch</li>
				</capacities>
				<power>18</power>
				<cooldownTime>1.2</cooldownTime>
				<linkedBodyPartsGroup>FrontRightClaws</linkedBodyPartsGroup>
				<surpriseAttack>
					<extraMeleeDamages>
						<li>
							<def>Stun</def>
							<amount>10</amount>
						</li>
					</extraMeleeDamages>
				</surpriseAttack>
			</li>
			<!-- head -->
			<li>
				<label>head</label>
				<capacities>
					<li>Blunt</li>
				</capacities>
				<power>9</power>
				<cooldownTime>2</cooldownTime>
				<linkedBodyPartsGroup>HeadAttackTool</linkedBodyPartsGroup>
				<ensureLinkedBodyPartsGroupAlwaysUsable>true</ensureLinkedBodyPartsGroupAlwaysUsable>
				<chanceFactor>0.2</chanceFactor>
			</li>
		</tools>
		<comps>
			<li Class="CompProperties_Milkable">
				<milkDef>ESCP_SprigganSap</milkDef>
				<milkIntervalDays>5</milkIntervalDays>
				<milkAmount>18</milkAmount>
				<milkFemaleOnly>false</milkFemaleOnly>
			</li>
			<li Class="ESCP_Spriggan.CompProperties_SprigganAnimalControl">
				<maxRange>10</maxRange>
				<maxNumberControlled>2</maxNumberControlled>
				<fleckDef>PsycastPsychicEffect</fleckDef>
				<soundDef>PsychicInsanityLanceCast</soundDef>
			</li>
		</comps>
		<race>
			<baseBodySize>1.4</baseBodySize>
			<baseHealthScale>1.8</baseHealthScale>
			<wildness>0.90</wildness>
			<wildBiomes>
				<TemperateForest>0.005</TemperateForest>
				<BorealForest>0.005</BorealForest>
				<TropicalRainforest>0.005</TropicalRainforest>
				<Tundra>0.005</Tundra>
				<ColdBog>0.005</ColdBog>
				<AridShrubland>0.005</AridShrubland>
				<Desert>0.005</Desert>
				<TropicalSwamp>0.005</TropicalSwamp>
				<!-- Biomes! -->
				<BiomesIslands_TemperateIsland MayRequire="BiomesTeam.BiomesIslands">0.005</BiomesIslands_TemperateIsland>
				<BiomesIslands_TemperateArchipelago MayRequire="BiomesTeam.BiomesIslands">0.005</BiomesIslands_TemperateArchipelago>
				<BiomesIslands_BorealIsland MayRequire="BiomesTeam.BiomesIslands">0.005</BiomesIslands_BorealIsland>
				<BiomesIslands_BorealArchipelago MayRequire="BiomesTeam.BiomesIslands">0.005</BiomesIslands_BorealArchipelago>
				<BiomesIslands_TropicalIsland MayRequire="BiomesTeam.BiomesIslands">0.005</BiomesIslands_TropicalIsland>
				<BiomesIslands_TropicalArchipelago MayRequire="BiomesTeam.BiomesIslands">0.005</BiomesIslands_TropicalArchipelago>
				<BiomesIslands_DesertIsland MayRequire="BiomesTeam.BiomesIslands">0.005</BiomesIslands_DesertIsland>
				<BiomesIslands_DesertArchipelago MayRequire="BiomesTeam.BiomesIslands">0.005</BiomesIslands_DesertArchipelago>
				<BiomesIslands_TundraIsland MayRequire="BiomesTeam.BiomesIslands">0.005</BiomesIslands_TundraIsland>
				<BiomesIslands_TundraArchipelago MayRequire="BiomesTeam.BiomesIslands">0.005</BiomesIslands_TundraArchipelago>
				<!-- Regrowth -->
				<RG-VIS_VulcanicIceSheet MayRequire="ReGrowth.BOTR.VolcanicIceSheet">0.005</RG-VIS_VulcanicIceSheet>
				<RG_AspenForest MayRequire="ReGrowth.BOTR.AspenForest">0.005</RG_AspenForest>
				<RG_BoilingForest MayRequire="regrowth.botr.boilingforest">0.005</RG_BoilingForest>
				<!-- More Vanilla Biomes -->
				<ZBiome_AlpineMeadow MayRequire="zylle.MoreVanillaBiomes">0.005</ZBiome_AlpineMeadow>
				<ZBiome_CloudForest MayRequire="zylle.MoreVanillaBiomes">0.005</ZBiome_CloudForest>
				<ZBiome_DesertOasis MayRequire="zylle.MoreVanillaBiomes">0.005</ZBiome_DesertOasis>
				<ZBiome_Marsh MayRequire="zylle.MoreVanillaBiomes">0.005</ZBiome_Marsh>
				<ZBiome_CoastalDunes MayRequire="zylle.MoreVanillaBiomes">0.005</ZBiome_CoastalDunes>
				<!-- Alpha Biomes -->
				<AB_PyroclasticConflagration MayRequire="sarg.alphabiomes">0.005</AB_PyroclasticConflagration>
				<AB_GallatrossGraveyard MayRequire="sarg.alphabiomes">0.005</AB_GallatrossGraveyard>
				<AB_TarPits MayRequire="sarg.alphabiomes">0.005</AB_TarPits>
				<AB_PropaneLakes MayRequire="sarg.alphabiomes">0.005</AB_PropaneLakes>
				<!-- Advanced Biomes -->
				<Volcano MayRequire="Mlie.AdvancedBiomes">0.005</Volcano>
				<Wetland MayRequire="Mlie.AdvancedBiomes">0.005</Wetland>
				<!-- Winter taiga -->
				<WinterTaiga MayRequire="reel.FrozenForest">0.005</WinterTaiga>
			</wildBiomes>
		</race>
	</ThingDef>
	<PawnKindDef ParentName="ESCP_SprigganKindBase">
		<combatPower>200</combatPower>
		<defName>ESCP_Spriggan_EarthMother</defName>
		<label>spriggan earth mother</label>
		<race>ESCP_Spriggan_EarthMother</race>
		<lifeStages>
			<li>
				<label>spriggan earth mother sproutling</label>
				<labelPlural>spriggan earth mother sproutlings</labelPlural>
				<bodyGraphicData>
					<texPath>Things/Pawn/Animal/ESCP_Spriggan/SprigganEarthMother</texPath>
					<drawSize>1.4</drawSize>
				</bodyGraphicData>
				<dessicatedBodyGraphicData>
					<texPath>Things/Pawn/Animal/ESCP_Spriggan/Dessicated_Spriggan</texPath>
					<drawSize>1.4</drawSize>
				</dessicatedBodyGraphicData>
			</li>
			<li>
				<label>spriggan earth mother sapling</label>
				<labelPlural>spriggan earth mother saplings</labelPlural>
				<bodyGraphicData>
					<texPath>Things/Pawn/Animal/ESCP_Spriggan/SprigganEarthMother</texPath>
					<drawSize>1.6</drawSize>
					<shadowData>
						<volume>(0.3, 0.3, 0.3)</volume>
						<offset>(0,0,-0.3)</offset>
					</shadowData>
				</bodyGraphicData>
				<dessicatedBodyGraphicData>
					<texPath>Things/Pawn/Animal/ESCP_Spriggan/Dessicated_Spriggan</texPath>
					<drawSize>1.6</drawSize>
				</dessicatedBodyGraphicData>
			</li>
			<li>
				<bodyGraphicData>
					<texPath>Things/Pawn/Animal/ESCP_Spriggan/SprigganEarthMother</texPath>
					<drawSize>1.8</drawSize>
					<shadowData>
						<volume>(0.4, 0.4, 0.4)</volume>
						<offset>(0,0,-0.1)</offset>
					</shadowData>
				</bodyGraphicData>
				<dessicatedBodyGraphicData>
					<texPath>Things/Pawn/Animal/ESCP_Spriggan/Dessicated_Spriggan</texPath>
					<drawSize>1.8</drawSize>
				</dessicatedBodyGraphicData>
				<butcherBodyPart>
					<bodyPartGroup>ESCP_TaprootGroup</bodyPartGroup>
					<thing>ESCP_SprigganTaproot_Mother</thing>
				</butcherBodyPart>
			</li>
		</lifeStages>
	</PawnKindDef>
</Defs>
